{
  "$id": "runme.runner.v2.ProgramConfig.CommandList.schema.strict.json",
  "$schema": "https://json-schema.org/draft/2020-12/schema",
  "additionalProperties": false,
  "properties": {
    "items": {
      "description": "commands are commands to be executed by the program.\n The commands are joined and executed as a script.\n For example: [\"echo 'Hello, World'\", \"ls -l /etc\"].",
      "items": {
        "type": "string"
      },
      "type": "array"
    }
  },
  "title": "Command List",
  "type": "object"
}
